[
  {
    "id": "cc16f606-7061-4a9f-b5ac-82059fea872e",
    "title": "To Do",
    "cards": []
  },
  {
    "id": "69a7b388-7ac4-4c01-bea8-a98a2fa5b44a",
    "title": "First Column",
    "cards": [
      {
        "id": "383a261a-84df-44c9-89d3-daa480c57115",
        "title": "third Card",
        "description": "Added By user 2"
      },
      {
        "id": "0c246915-9658-457d-9fc0-34a1b7a58957",
        "title": "Second Card",
        "description": "Added by user 2"
      },
      {
        "id": "a27dead5-f8cc-4680-991d-8803796057fa",
        "title": "First Card",
        "description": "added by user 1"
      },
      {
        "id": "ed74a1ab-ed8c-476e-8f55-c605717fc6b1",
        "title": "fourth Card",
        "description": "added  by user 2"
      },
      {
        "id": "4364a0eb-19d4-4e42-91a1-838291a10b58",
        "title": "fifth card",
        "description": "added by user 2"
      }
    ]
  }
]